{"accuracy": 0.7166666666666667, "correct_count": 172, "total_count": 240}
{"id": 1, "model_name": "yi-large-fc", "test_category": "relevance", "valid": false, "error": ["Valid syntax. Successfully decode AST when it should not."], "error_type": "relevance_error:decoder_success", "model_result": [{"calculate_area_of_triangle": "{\"base\": 10, \"height\": 5}"}], "decoded_result": [{"calculate_area_of_triangle": {"base": 10, "height": 5}}]}
{"id": 3, "model_name": "yi-large-fc", "test_category": "relevance", "valid": false, "error": ["Valid syntax. Successfully decode AST when it should not."], "error_type": "relevance_error:decoder_success", "model_result": [{"solve_quadratic_equation": "{\"a\":3,\"b\":-2,\"c\":-5}"}], "decoded_result": [{"solve_quadratic_equation": {"a": 3, "b": -2, "c": -5}}]}
{"id": 8, "model_name": "yi-large-fc", "test_category": "relevance", "valid": false, "error": ["Valid syntax. Successfully decode AST when it should not."], "error_type": "relevance_error:decoder_success", "model_result": [{"math_integral_calculator": "{\"function\":\"3*x**2\",\"lower_bound\":1,\"upper_bound\":5}"}], "decoded_result": [{"math_integral_calculator": {"function": "3*x**2", "lower_bound": 1, "upper_bound": 5}}]}
{"id": 10, "model_name": "yi-large-fc", "test_category": "relevance", "valid": false, "error": ["Valid syntax. Successfully decode AST when it should not."], "error_type": "relevance_error:decoder_success", "model_result": [{"DefiniteIntegral": "{\"function_to_integrate\": \"x**2\", \"lower_limit\": 1, \"upper_limit\": 3}"}], "decoded_result": [{"DefiniteIntegral": {"function_to_integrate": "x**2", "lower_limit": 1, "upper_limit": 3}}]}
{"id": 16, "model_name": "yi-large-fc", "test_category": "relevance", "valid": false, "error": ["Valid syntax. Successfully decode AST when it should not."], "error_type": "relevance_error:decoder_success", "model_result": [{"get_movie_releases": "{\"start_date\":\"2024-08-01\",\"end_date\":\"2024-08-08\"}"}], "decoded_result": [{"get_movie_releases": {"start_date": "2024-08-01", "end_date": "2024-08-08"}}]}
{"id": 20, "model_name": "yi-large-fc", "test_category": "relevance", "valid": false, "error": ["Valid syntax. Successfully decode AST when it should not."], "error_type": "relevance_error:decoder_success", "model_result": [{"cone_volume": "{\"radius\":3,\"height\":5}"}], "decoded_result": [{"cone_volume": {"radius": 3, "height": 5}}]}
{"id": 27, "model_name": "yi-large-fc", "test_category": "relevance", "valid": false, "error": ["Valid syntax. Successfully decode AST when it should not."], "error_type": "relevance_error:decoder_success", "model_result": [{"thermodynamics_calc_gas_pressure": "{\"volume\":2,\"initial_temperature\":25,\"final_temperature\":100}"}], "decoded_result": [{"thermodynamics_calc_gas_pressure": {"volume": 2, "initial_temperature": 25, "final_temperature": 100}}]}
{"id": 28, "model_name": "yi-large-fc", "test_category": "relevance", "valid": false, "error": ["Valid syntax. Successfully decode AST when it should not."], "error_type": "relevance_error:decoder_success", "model_result": [{"calculate_heat": "{\"mass\":3,\"specific_heat\":4.184,\"change_in_temp\":4}"}], "decoded_result": [{"calculate_heat": {"mass": 3, "specific_heat": 4.184, "change_in_temp": 4}}]}
{"id": 34, "model_name": "yi-large-fc", "test_category": "relevance", "valid": false, "error": ["Valid syntax. Successfully decode AST when it should not."], "error_type": "relevance_error:decoder_success", "model_result": [{"identify_species": "{\"sequence\":\"ATCG\"}"}], "decoded_result": [{"identify_species": {"sequence": "ATCG"}}]}
{"id": 36, "model_name": "yi-large-fc", "test_category": "relevance", "valid": false, "error": ["Valid syntax. Successfully decode AST when it should not."], "error_type": "relevance_error:decoder_success", "model_result": [{"get_genetic_traits": "{\"species\":\"Lion\"}"}], "decoded_result": [{"get_genetic_traits": {"species": "Lion"}}]}
{"id": 39, "model_name": "yi-large-fc", "test_category": "relevance", "valid": false, "error": ["Valid syntax. Successfully decode AST when it should not."], "error_type": "relevance_error:decoder_success", "model_result": [{"retrieve_scientific_paper": "{\"topic\":\"global warming\"}"}], "decoded_result": [{"retrieve_scientific_paper": {"topic": "global warming"}}]}
{"id": 41, "model_name": "yi-large-fc", "test_category": "relevance", "valid": false, "error": ["Valid syntax. Successfully decode AST when it should not."], "error_type": "relevance_error:decoder_success", "model_result": [{"get_air_quality": "{\"city\":\"Los Angeles\"}"}], "decoded_result": [{"get_air_quality": {"city": "Los Angeles"}}]}
{"id": 45, "model_name": "yi-large-fc", "test_category": "relevance", "valid": false, "error": ["Valid syntax. Successfully decode AST when it should not."], "error_type": "relevance_error:decoder_success", "model_result": [{"gene_sequencer": "{\"species\":\"whales\",\"mutation_rate\":0.01,\"evolution_duration\":100000}"}], "decoded_result": [{"gene_sequencer": {"species": "whales", "mutation_rate": 0.01, "evolution_duration": 100000}}]}
{"id": 46, "model_name": "yi-large-fc", "test_category": "relevance", "valid": false, "error": ["Valid syntax. Successfully decode AST when it should not."], "error_type": "relevance_error:decoder_success", "model_result": [{"math_sin": "{\"degrees\": 45}"}], "decoded_result": [{"math_sin": {"degrees": 45}}]}
{"id": 47, "model_name": "yi-large-fc", "test_category": "relevance", "valid": false, "error": ["Valid syntax. Successfully decode AST when it should not."], "error_type": "relevance_error:decoder_success", "model_result": [{"get_exchange_rate": "{\"base_currency\":\"USD\",\"target_currency\":\"INR\"}"}], "decoded_result": [{"get_exchange_rate": {"base_currency": "USD", "target_currency": "INR"}}]}
{"id": 51, "model_name": "yi-large-fc", "test_category": "relevance", "valid": false, "error": ["Valid syntax. Successfully decode AST when it should not."], "error_type": "relevance_error:decoder_success", "model_result": [{"convert_celsius_to_fahrenheit": "{\"celsius\":20,\"precision\":2}"}], "decoded_result": [{"convert_celsius_to_fahrenheit": {"celsius": 20, "precision": 2}}]}
{"id": 52, "model_name": "yi-large-fc", "test_category": "relevance", "valid": false, "error": ["Valid syntax. Successfully decode AST when it should not."], "error_type": "relevance_error:decoder_success", "model_result": [{"fibonacci": "20"}], "decoded_result": [{"fibonacci": 20}]}
{"id": 60, "model_name": "yi-large-fc", "test_category": "relevance", "valid": false, "error": ["Valid syntax. Successfully decode AST when it should not."], "error_type": "relevance_error:decoder_success", "model_result": [{"power_calculator": "{\"base\": 2, \"exponent\": 5}"}], "decoded_result": [{"power_calculator": {"base": 2, "exponent": 5}}]}
{"id": 66, "model_name": "yi-large-fc", "test_category": "relevance", "valid": false, "error": ["Valid syntax. Successfully decode AST when it should not."], "error_type": "relevance_error:decoder_success", "model_result": [{"probability_determine_population": "{\"probability\":0.3,\"sample_size\":20}"}], "decoded_result": [{"probability_determine_population": {"probability": 0.3, "sample_size": 20}}]}
{"id": 69, "model_name": "yi-large-fc", "test_category": "relevance", "valid": false, "error": ["Valid syntax. Successfully decode AST when it should not."], "error_type": "relevance_error:decoder_success", "model_result": [{"statistics_calculate_p_value": "{\"sample_mean\":98.2,\"population_mean\":98.6,\"sample_std_dev\":1.4,\"sample_size\":40}"}], "decoded_result": [{"statistics_calculate_p_value": {"sample_mean": 98.2, "population_mean": 98.6, "sample_std_dev": 1.4, "sample_size": 40}}]}
{"id": 72, "model_name": "yi-large-fc", "test_category": "relevance", "valid": false, "error": ["Valid syntax. Successfully decode AST when it should not."], "error_type": "relevance_error:decoder_success", "model_result": [{"calculate_profit_margin": "{\"revenue\":200000,\"expenses\":150000}"}], "decoded_result": [{"calculate_profit_margin": {"revenue": 200000, "expenses": 150000}}]}
{"id": 78, "model_name": "yi-large-fc", "test_category": "relevance", "valid": false, "error": ["Valid syntax. Successfully decode AST when it should not."], "error_type": "relevance_error:decoder_success", "model_result": [{"search_movies": "{\"genre\":\"horror\"}"}], "decoded_result": [{"search_movies": {"genre": "horror"}}]}
{"id": 82, "model_name": "yi-large-fc", "test_category": "relevance", "valid": false, "error": ["Valid syntax. Successfully decode AST when it should not."], "error_type": "relevance_error:decoder_success", "model_result": [{"google_search": "{\"search_query\": \"horror movies\", \"num_results\": 5}"}], "decoded_result": [{"google_search": {"search_query": "horror movies", "num_results": 5}}]}
{"id": 83, "model_name": "yi-large-fc", "test_category": "relevance", "valid": false, "error": ["Valid syntax. Successfully decode AST when it should not."], "error_type": "relevance_error:decoder_success", "model_result": [{"get_news": "{}"}], "decoded_result": [{"get_news": {}}]}
{"id": 85, "model_name": "yi-large-fc", "test_category": "relevance", "valid": false, "error": ["Valid syntax. Successfully decode AST when it should not."], "error_type": "relevance_error:decoder_success", "model_result": [{"get_stock_data": "{\"company_name\":\"Lakers\",\"date\":\"2024-08-07\"}"}, {"get_stock_data": "{\"company_name\":\"Celtics\",\"date\":\"2024-08-07\"}"}], "decoded_result": [{"get_stock_data": {"company_name": "Lakers", "date": "2024-08-07"}}, {"get_stock_data": {"company_name": "Celtics", "date": "2024-08-07"}}]}
{"id": 87, "model_name": "yi-large-fc", "test_category": "relevance", "valid": false, "error": ["Valid syntax. Successfully decode AST when it should not."], "error_type": "relevance_error:decoder_success", "model_result": [{"law_info_get_penalty": "{\"crime\":\"burglary\",\"state\":\"California\"}"}], "decoded_result": [{"law_info_get_penalty": {"crime": "burglary", "state": "California"}}]}
{"id": 88, "model_name": "yi-large-fc", "test_category": "relevance", "valid": false, "error": ["Valid syntax. Successfully decode AST when it should not."], "error_type": "relevance_error:decoder_success", "model_result": [{"legal_case_file": "{\"court\":\"Supreme Court of California\",\"case_type\":\"Appeal\",\"documents\":[\"brief.pdf\",\"exhibits.zip\"]}"}], "decoded_result": [{"legal_case_file": {"court": "Supreme Court of California", "case_type": "Appeal", "documents": ["brief.pdf", "exhibits.zip"]}}]}
{"id": 89, "model_name": "yi-large-fc", "test_category": "relevance", "valid": false, "error": ["Valid syntax. Successfully decode AST when it should not."], "error_type": "relevance_error:decoder_success", "model_result": [{"best_movies": "{\"year\":2020,\"genre\":\"Crime-Thriller\"}"}], "decoded_result": [{"best_movies": {"year": 2020, "genre": "Crime-Thriller"}}]}
{"id": 100, "model_name": "yi-large-fc", "test_category": "relevance", "valid": false, "error": ["Valid syntax. Successfully decode AST when it should not."], "error_type": "relevance_error:decoder_success", "model_result": [{"lawsuit_search": "{\"location\":\"Texas\",\"subject\":\"traffic laws\",\"year\":2024}"}], "decoded_result": [{"lawsuit_search": {"location": "Texas", "subject": "traffic laws", "year": 2024}}]}
{"id": 104, "model_name": "yi-large-fc", "test_category": "relevance", "valid": false, "error": ["Valid syntax. Successfully decode AST when it should not."], "error_type": "relevance_error:decoder_success", "model_result": [{"weather_forecast_get": "{\"location\":\"New York, NY\"}"}], "decoded_result": [{"weather_forecast_get": {"location": "New York, NY"}}]}
{"id": 106, "model_name": "yi-large-fc", "test_category": "relevance", "valid": false, "error": ["Valid syntax. Successfully decode AST when it should not."], "error_type": "relevance_error:decoder_success", "model_result": [{"external_api_call": "{\"function_name\": \"top_pollinators\", \"args\": {\"region\": \"South America\", \"limit\": 5}}"}], "decoded_result": [{"external_api_call": {"function_name": "top_pollinators", "args": {"region": "South America", "limit": 5}}}]}
{"id": 111, "model_name": "yi-large-fc", "test_category": "relevance", "valid": false, "error": ["Valid syntax. Successfully decode AST when it should not."], "error_type": "relevance_error:decoder_success", "model_result": [{"get_average_temperature": "{\"location\":\"Los Angeles\",\"month\":\"December\"}"}], "decoded_result": [{"get_average_temperature": {"location": "Los Angeles", "month": "December"}}]}
{"id": 112, "model_name": "yi-large-fc", "test_category": "relevance", "valid": false, "error": ["Valid syntax. Successfully decode AST when it should not."], "error_type": "relevance_error:decoder_success", "model_result": [{"geo_location_based_products_fetch_eco_friendly_products": "{\"location\":\"Seattle, WA\",\"product_category\":\"Yoga Mats\",\"availability\":\"Instore\"}"}], "decoded_result": [{"geo_location_based_products_fetch_eco_friendly_products": {"location": "Seattle, WA", "product_category": "Yoga Mats", "availability": "Instore"}}]}
{"id": 114, "model_name": "yi-large-fc", "test_category": "relevance", "valid": false, "error": ["Valid syntax. Successfully decode AST when it should not."], "error_type": "relevance_error:decoder_success", "model_result": [{"find_pois": "{\"location\":\"London\",\"category\":[\"Restaurants\"]}"}], "decoded_result": [{"find_pois": {"location": "London", "category": ["Restaurants"]}}]}
{"id": 116, "model_name": "yi-large-fc", "test_category": "relevance", "valid": false, "error": ["Valid syntax. Successfully decode AST when it should not."], "error_type": "relevance_error:decoder_success", "model_result": [{"calculate_distance": "{\"origin\":{\"latitude\":42.3601,\"longitude\":-71.0589},\"destination\":{\"latitude\":40.7128,\"longitude\":-74.006},\"speed\":65}"}], "decoded_result": [{"calculate_distance": {"origin": {"latitude": 42.3601, "longitude": -71.0589}, "destination": {"latitude": 40.7128, "longitude": -74.006}, "speed": 65}}]}
{"id": 122, "model_name": "yi-large-fc", "test_category": "relevance", "valid": false, "error": ["Valid syntax. Successfully decode AST when it should not."], "error_type": "relevance_error:decoder_success", "model_result": [{"medical_records_get_disease_info": "{\"disease_name\":\"motor neuron disease\"}"}], "decoded_result": [{"medical_records_get_disease_info": {"disease_name": "motor neuron disease"}}]}
{"id": 124, "model_name": "yi-large-fc", "test_category": "relevance", "valid": false, "error": ["Valid syntax. Successfully decode AST when it should not."], "error_type": "relevance_error:decoder_success", "model_result": [{"get_calories": "{\"food_item\": \"Big Mac\"}"}], "decoded_result": [{"get_calories": {"food_item": "Big Mac"}}]}
{"id": 125, "model_name": "yi-large-fc", "test_category": "relevance", "valid": false, "error": ["Valid syntax. Successfully decode AST when it should not."], "error_type": "relevance_error:decoder_success", "model_result": [{"get_social_trends": "{\"category\":\"technology\",\"region\":\"worldwide\"}"}], "decoded_result": [{"get_social_trends": {"category": "technology", "region": "worldwide"}}]}
{"id": 128, "model_name": "yi-large-fc", "test_category": "relevance", "valid": false, "error": ["Valid syntax. Successfully decode AST when it should not."], "error_type": "relevance_error:decoder_success", "model_result": [{"sentiment_analysis_twitter": "{\"topic\":\"new iPhone release\",\"language\":\"en\"}"}], "decoded_result": [{"sentiment_analysis_twitter": {"topic": "new iPhone release", "language": "en"}}]}
{"id": 134, "model_name": "yi-large-fc", "test_category": "relevance", "valid": false, "error": ["Valid syntax. Successfully decode AST when it should not."], "error_type": "relevance_error:decoder_success", "model_result": [{"get_battle_details": "{\"battle_name\":\"NBA final\",\"year\":2023}"}], "decoded_result": [{"get_battle_details": {"battle_name": "NBA final", "year": 2023}}]}
{"id": 142, "model_name": "yi-large-fc", "test_category": "relevance", "valid": false, "error": ["Valid syntax. Successfully decode AST when it should not."], "error_type": "relevance_error:decoder_success", "model_result": [{"get_element_properties": "{\"element_name\":\"Hydrogen\"}"}], "decoded_result": [{"get_element_properties": {"element_name": "Hydrogen"}}]}
{"id": 147, "model_name": "yi-large-fc", "test_category": "relevance", "valid": false, "error": ["Valid syntax. Successfully decode AST when it should not."], "error_type": "relevance_error:decoder_success", "model_result": [{"mix_colors": "{\"color1\": \"#FAEBD7\", \"color2\": \"#00FFFF\"}"}], "decoded_result": [{"mix_colors": {"color1": "#FAEBD7", "color2": "#00FFFF"}}]}
{"id": 155, "model_name": "yi-large-fc", "test_category": "relevance", "valid": false, "error": ["Valid syntax. Successfully decode AST when it should not."], "error_type": "relevance_error:decoder_success", "model_result": [{"sculpture_info_find_creator": "{\"sculpture_name\":\"Camp Nou Stadium\"}"}], "decoded_result": [{"sculpture_info_find_creator": {"sculpture_name": "Camp Nou Stadium"}}]}
{"id": 163, "model_name": "yi-large-fc", "test_category": "relevance", "valid": false, "error": ["Valid syntax. Successfully decode AST when it should not."], "error_type": "relevance_error:decoder_success", "model_result": [{"get_museum_artists": "{\"museum_name\":\"National Museum of Dance\",\"period\":\"19th Century\"}"}], "decoded_result": [{"get_museum_artists": {"museum_name": "National Museum of Dance", "period": "19th Century"}}]}
{"id": 165, "model_name": "yi-large-fc", "test_category": "relevance", "valid": false, "error": ["Valid syntax. Successfully decode AST when it should not."], "error_type": "relevance_error:decoder_success", "model_result": [{"search_music_instrument_players": "{\"instrument\":\"vocalists\",\"genre\":\"Jazz\"}"}], "decoded_result": [{"search_music_instrument_players": {"instrument": "vocalists", "genre": "Jazz"}}]}
{"id": 166, "model_name": "yi-large-fc", "test_category": "relevance", "valid": false, "error": ["Valid syntax. Successfully decode AST when it should not."], "error_type": "relevance_error:decoder_success", "model_result": [{"get_instrument_info": "{\"instrument_name\":\"cello\",\"detail\":\"type\"}"}], "decoded_result": [{"get_instrument_info": {"instrument_name": "cello", "detail": "type"}}]}
{"id": 170, "model_name": "yi-large-fc", "test_category": "relevance", "valid": false, "error": ["Valid syntax. Successfully decode AST when it should not."], "error_type": "relevance_error:decoder_success", "model_result": [{"sports_game_find_games": "{\"venue\":\"Madison Square Garden\"}"}], "decoded_result": [{"sports_game_find_games": {"venue": "Madison Square Garden"}}]}
{"id": 181, "model_name": "yi-large-fc", "test_category": "relevance", "valid": false, "error": ["Valid syntax. Successfully decode AST when it should not."], "error_type": "relevance_error:decoder_success", "model_result": [{"sports_analyzer_get_schedule": "{\"date\":\"2024-08-08\",\"sport\":\"cricket\"}"}], "decoded_result": [{"sports_analyzer_get_schedule": {"date": "2024-08-08", "sport": "cricket"}}]}
{"id": 182, "model_name": "yi-large-fc", "test_category": "relevance", "valid": false, "error": ["Valid syntax. Successfully decode AST when it should not."], "error_type": "relevance_error:decoder_success", "model_result": [{"soccer_stats_get_last_match_result": "{\"team1\":\"Real Madrid\",\"team2\":\"Barcelona\"}"}], "decoded_result": [{"soccer_stats_get_last_match_result": {"team1": "Real Madrid", "team2": "Barcelona"}}]}
{"id": 183, "model_name": "yi-large-fc", "test_category": "relevance", "valid": false, "error": ["Valid syntax. Successfully decode AST when it should not."], "error_type": "relevance_error:decoder_success", "model_result": [{"get_nba_player_stats": "{\"player_name\":\"Michael Jordan\",\"stat_type\":\"championships\"}"}], "decoded_result": [{"get_nba_player_stats": {"player_name": "Michael Jordan", "stat_type": "championships"}}]}
{"id": 189, "model_name": "yi-large-fc", "test_category": "relevance", "valid": false, "error": ["Valid syntax. Successfully decode AST when it should not."], "error_type": "relevance_error:decoder_success", "model_result": [{"sports_ranking_get_champion": "{\"event\":\"World Series\",\"year\":2020}"}], "decoded_result": [{"sports_ranking_get_champion": {"event": "World Series", "year": 2020}}]}
{"id": 191, "model_name": "yi-large-fc", "test_category": "relevance", "valid": false, "error": ["Valid syntax. Successfully decode AST when it should not."], "error_type": "relevance_error:decoder_success", "model_result": [{"sports_team_standing": "{\"team_name\":\"Serena Williams\",\"league\":\"WTA\"}"}], "decoded_result": [{"sports_team_standing": {"team_name": "Serena Williams", "league": "WTA"}}]}
{"id": 194, "model_name": "yi-large-fc", "test_category": "relevance", "valid": false, "error": ["Valid syntax. Successfully decode AST when it should not."], "error_type": "relevance_error:decoder_success", "model_result": [{"get_sport_team_details": "{\"team_name\":\"Los Angeles Lakers\",\"details\":[\"roster\"]}"}], "decoded_result": [{"get_sport_team_details": {"team_name": "Los Angeles Lakers", "details": ["roster"]}}]}
{"id": 202, "model_name": "yi-large-fc", "test_category": "relevance", "valid": false, "error": ["Valid syntax. Successfully decode AST when it should not."], "error_type": "relevance_error:decoder_success", "model_result": [{"find_nearby_places": "{\"location\":\"San Francisco, CA\"}"}], "decoded_result": [{"find_nearby_places": {"location": "San Francisco, CA"}}]}
{"id": 214, "model_name": "yi-large-fc", "test_category": "relevance", "valid": false, "error": ["Valid syntax. Successfully decode AST when it should not."], "error_type": "relevance_error:decoder_success", "model_result": [{"restaurant_finder": "{\"cuisine\":\"pizza\",\"location\":\"Boston\"}"}], "decoded_result": [{"restaurant_finder": {"cuisine": "pizza", "location": "Boston"}}]}
{"id": 215, "model_name": "yi-large-fc", "test_category": "relevance", "valid": false, "error": ["Valid syntax. Successfully decode AST when it should not."], "error_type": "relevance_error:decoder_success", "model_result": [{"find_best_restaurant": "{\"location\": \"Los Angeles\", \"cuisine\": \"Sushi\"}"}], "decoded_result": [{"find_best_restaurant": {"location": "Los Angeles", "cuisine": "Sushi"}}]}
{"id": 216, "model_name": "yi-large-fc", "test_category": "relevance", "valid": false, "error": ["Valid syntax. Successfully decode AST when it should not."], "error_type": "relevance_error:decoder_success", "model_result": [{"get_travel_time": "{\"origin\":\"San Francisco, CA\",\"destination\":\"Los Angeles, CA\",\"mode\":\"driving\"}"}], "decoded_result": [{"get_travel_time": {"origin": "San Francisco, CA", "destination": "Los Angeles, CA", "mode": "driving"}}]}
{"id": 224, "model_name": "yi-large-fc", "test_category": "relevance", "valid": false, "error": ["Valid syntax. Successfully decode AST when it should not."], "error_type": "relevance_error:decoder_success", "model_result": [{"grocery_shop_find_specific_product": "{\"city\":\"Chicago\",\"product\":\"sourdough bread\"}"}], "decoded_result": [{"grocery_shop_find_specific_product": {"city": "Chicago", "product": "sourdough bread"}}]}
{"id": 226, "model_name": "yi-large-fc", "test_category": "relevance", "valid": false, "error": ["Valid syntax. Successfully decode AST when it should not."], "error_type": "relevance_error:decoder_success", "model_result": [{"get_city_population": "{\"city\":\"New York\"}"}], "decoded_result": [{"get_city_population": {"city": "New York"}}]}
{"id": 227, "model_name": "yi-large-fc", "test_category": "relevance", "valid": false, "error": ["Valid syntax. Successfully decode AST when it should not."], "error_type": "relevance_error:decoder_success", "model_result": [{"get_local_time": "{\"timezone\": \"Europe/London\", \"date_format\": \"YYYY-MM-DD HH:mm:ss\"}"}], "decoded_result": [{"get_local_time": {"timezone": "Europe/London", "date_format": "YYYY-MM-DD HH:mm:ss"}}]}
{"id": 229, "model_name": "yi-large-fc", "test_category": "relevance", "valid": false, "error": ["Valid syntax. Successfully decode AST when it should not."], "error_type": "relevance_error:decoder_success", "model_result": [{"get_local_time": "{\"location\":\"Sydney, Australia\"}"}], "decoded_result": [{"get_local_time": {"location": "Sydney, Australia"}}]}
{"id": 230, "model_name": "yi-large-fc", "test_category": "relevance", "valid": false, "error": ["Valid syntax. Successfully decode AST when it should not."], "error_type": "relevance_error:decoder_success", "model_result": [{"find_restaurants": "{\"location\":\"Tokyo\"}"}], "decoded_result": [{"find_restaurants": {"location": "Tokyo"}}]}
{"id": 233, "model_name": "yi-large-fc", "test_category": "relevance", "valid": false, "error": ["Valid syntax. Successfully decode AST when it should not."], "error_type": "relevance_error:decoder_success", "model_result": [{"hotel_search_find_hotels": "{\"location\":\"New York, NY\",\"amenities\":[\"Breakfast\",\"Fitness Centre\"]}"}], "decoded_result": [{"hotel_search_find_hotels": {"location": "New York, NY", "amenities": ["Breakfast", "Fitness Centre"]}}]}
{"id": 234, "model_name": "yi-large-fc", "test_category": "relevance", "valid": false, "error": ["Valid syntax. Successfully decode AST when it should not."], "error_type": "relevance_error:decoder_success", "model_result": [{"convert_usd_to_gbp": "{\"amount\":20}"}], "decoded_result": [{"convert_usd_to_gbp": {"amount": 20}}]}
{"id": 236, "model_name": "yi-large-fc", "test_category": "relevance", "valid": false, "error": ["Valid syntax. Successfully decode AST when it should not."], "error_type": "relevance_error:decoder_success", "model_result": [{"search": "{\"query\": \"What is the best movie in 2020?\"}"}], "decoded_result": [{"search": {"query": "What is the best movie in 2020?"}}]}
{"id": 237, "model_name": "yi-large-fc", "test_category": "relevance", "valid": false, "error": ["Valid syntax. Successfully decode AST when it should not."], "error_type": "relevance_error:decoder_success", "model_result": [{"get_flight_duration": "{\"start_city\":\"London\",\"destination_city\":\"Tokyo\",\"flight_type\":\"non-stop\"}"}], "decoded_result": [{"get_flight_duration": {"start_city": "London", "destination_city": "Tokyo", "flight_type": "non-stop"}}]}
{"id": 239, "model_name": "yi-large-fc", "test_category": "relevance", "valid": false, "error": ["Valid syntax. Successfully decode AST when it should not."], "error_type": "relevance_error:decoder_success", "model_result": [{"pythagoras_theorem": "{\"a\":5,\"b\":6}"}], "decoded_result": [{"pythagoras_theorem": {"a": 5, "b": 6}}]}
{"id": 240, "model_name": "yi-large-fc", "test_category": "relevance", "valid": false, "error": ["Valid syntax. Successfully decode AST when it should not."], "error_type": "relevance_error:decoder_success", "model_result": [{"get_date": "{\"location_1\":\"San Francisco\",\"location_2\":\"Los Angeles\",\"unit\":\"kilometers\"}"}], "decoded_result": [{"get_date": {"location_1": "San Francisco", "location_2": "Los Angeles", "unit": "kilometers"}}]}