{"accuracy": 0.875, "correct_count": 210, "total_count": 240}
{"id": 8, "model_name": "THUDM_glm-4-9b-chat", "test_category": "relevance", "valid": false, "error": ["Valid syntax. Successfully decode AST when it should not."], "error_type": "relevance_error:decoder_success", "model_result": "math_integral_calculator\n{\"function\": \"3*x**2\", \"lower_bound\": 1, \"upper_bound\": 5}", "decoded_result": [{"math_integral_calculator": {"function": "3*x**2", "lower_bound": 1, "upper_bound": 5}}]}
{"id": 15, "model_name": "THUDM_glm-4-9b-chat", "test_category": "relevance", "valid": false, "error": ["Valid syntax. Successfully decode AST when it should not."], "error_type": "relevance_error:decoder_success", "model_result": "calculate_maximum_height\n{\"initial_velocity\": 5.0}", "decoded_result": [{"calculate_maximum_height": {"initial_velocity": 5.0}}]}
{"id": 28, "model_name": "THUDM_glm-4-9b-chat", "test_category": "relevance", "valid": false, "error": ["Valid syntax. Successfully decode AST when it should not."], "error_type": "relevance_error:decoder_success", "model_result": "calculate_heat\n{\"mass\": 3.0, \"specific_heat\": 4.184, \"change_in_temp\": 4.0}", "decoded_result": [{"calculate_heat": {"mass": 3.0, "specific_heat": 4.184, "change_in_temp": 4.0}}]}
{"id": 34, "model_name": "THUDM_glm-4-9b-chat", "test_category": "relevance", "valid": false, "error": ["Valid syntax. Successfully decode AST when it should not."], "error_type": "relevance_error:decoder_success", "model_result": "identify_species\n{\"sequence\": \"ATCG\", \"database\": \"GenBank\"}", "decoded_result": [{"identify_species": {"sequence": "ATCG", "database": "GenBank"}}]}
{"id": 39, "model_name": "THUDM_glm-4-9b-chat", "test_category": "relevance", "valid": false, "error": ["Valid syntax. Successfully decode AST when it should not."], "error_type": "relevance_error:decoder_success", "model_result": "retrieve_scientific_paper\n{\"topic\": \"global warming\", \"year\": \"None\", \"author\": \"None\"}", "decoded_result": [{"retrieve_scientific_paper": {"topic": "global warming", "year": "None", "author": "None"}}]}
{"id": 87, "model_name": "THUDM_glm-4-9b-chat", "test_category": "relevance", "valid": false, "error": ["Valid syntax. Successfully decode AST when it should not."], "error_type": "relevance_error:decoder_success", "model_result": "law_info_get_penalty\n{\"crime\": \"burglary\", \"state\": \"California\"}", "decoded_result": [{"law_info_get_penalty": {"crime": "burglary", "state": "California"}}]}
{"id": 98, "model_name": "THUDM_glm-4-9b-chat", "test_category": "relevance", "valid": false, "error": ["Valid syntax. Successfully decode AST when it should not."], "error_type": "relevance_error:decoder_success", "model_result": "file_lawsuit\n{\"defendant\": \"John Doe\", \"plaintiff\": \"Jane Smith\", \"jurisdiction\": \"New York, NY\"}", "decoded_result": [{"file_lawsuit": {"defendant": "John Doe", "plaintiff": "Jane Smith", "jurisdiction": "New York, NY"}}]}
{"id": 110, "model_name": "THUDM_glm-4-9b-chat", "test_category": "relevance", "valid": false, "error": ["Valid syntax. Successfully decode AST when it should not."], "error_type": "relevance_error:decoder_success", "model_result": "calculate_water_needs\n{\"plant_type\": \"cactus\", \"location\": \"Arizona\", \"season\": \"summer\"}", "decoded_result": [{"calculate_water_needs": {"plant_type": "cactus", "location": "Arizona", "season": "summer"}}]}
{"id": 113, "model_name": "THUDM_glm-4-9b-chat", "test_category": "relevance", "valid": false, "error": ["Valid syntax. Successfully decode AST when it should not."], "error_type": "relevance_error:decoder_success", "model_result": "geocode_address\n{\"address\": \"New York\"}", "decoded_result": [{"geocode_address": {"address": "New York"}}]}
{"id": 114, "model_name": "THUDM_glm-4-9b-chat", "test_category": "relevance", "valid": false, "error": ["Valid syntax. Successfully decode AST when it should not."], "error_type": "relevance_error:decoder_success", "model_result": "find_pois\n{\"location\": \"London\", \"category\": [\"Restaurants\"]}", "decoded_result": [{"find_pois": {"location": "London", "category": ["Restaurants"]}}]}
{"id": 119, "model_name": "THUDM_glm-4-9b-chat", "test_category": "relevance", "valid": false, "error": ["Valid syntax. Successfully decode AST when it should not."], "error_type": "relevance_error:decoder_success", "model_result": "playoff_brackets\n{\"year\": 1996, \"round\": \"Finals\"}", "decoded_result": [{"playoff_brackets": {"year": 1996, "round": "Finals"}}]}
{"id": 122, "model_name": "THUDM_glm-4-9b-chat", "test_category": "relevance", "valid": false, "error": ["Valid syntax. Successfully decode AST when it should not."], "error_type": "relevance_error:decoder_success", "model_result": "medical_records_get_disease_info\n{\"disease_name\": \"motor neuron disease\", \"include_statistics\": false}", "decoded_result": [{"medical_records_get_disease_info": {"disease_name": "motor neuron disease", "include_statistics": false}}]}
{"id": 125, "model_name": "THUDM_glm-4-9b-chat", "test_category": "relevance", "valid": false, "error": ["Valid syntax. Successfully decode AST when it should not."], "error_type": "relevance_error:decoder_success", "model_result": "get_social_trends\n{\"category\": \"technology\", \"region\": \"worldwide\"}", "decoded_result": [{"get_social_trends": {"category": "technology", "region": "worldwide"}}]}
{"id": 128, "model_name": "THUDM_glm-4-9b-chat", "test_category": "relevance", "valid": false, "error": ["Valid syntax. Successfully decode AST when it should not."], "error_type": "relevance_error:decoder_success", "model_result": "sentiment_analysis_twitter\n{\"topic\": \"new iPhone release\", \"language\": \"en\"}", "decoded_result": [{"sentiment_analysis_twitter": {"topic": "new iPhone release", "language": "en"}}]}
{"id": 161, "model_name": "THUDM_glm-4-9b-chat", "test_category": "relevance", "valid": false, "error": ["Valid syntax. Successfully decode AST when it should not."], "error_type": "relevance_error:decoder_success", "model_result": "most_frequent_visitor\n{\"museum_name\": \"Museum of Modern Art\", \"start_date\": \"2021-01-01\", \"end_date\": \"2021-12-31\", \"minimum_visits\": 1}", "decoded_result": [{"most_frequent_visitor": {"museum_name": "Museum of Modern Art", "start_date": "2021-01-01", "end_date": "2021-12-31", "minimum_visits": 1}}]}
{"id": 166, "model_name": "THUDM_glm-4-9b-chat", "test_category": "relevance", "valid": false, "error": ["Valid syntax. Successfully decode AST when it should not."], "error_type": "relevance_error:decoder_success", "model_result": "get_instrument_info\n{\"instrument_name\": \"cello\", \"detail\": \"type\"}", "decoded_result": [{"get_instrument_info": {"instrument_name": "cello", "detail": "type"}}]}
{"id": 183, "model_name": "THUDM_glm-4-9b-chat", "test_category": "relevance", "valid": false, "error": ["Valid syntax. Successfully decode AST when it should not."], "error_type": "relevance_error:decoder_success", "model_result": "get_nba_player_stats\n{\"player_name\": \"Michael Jordan\", \"stat_type\": \"championships\"}", "decoded_result": [{"get_nba_player_stats": {"player_name": "Michael Jordan", "stat_type": "championships"}}]}
{"id": 189, "model_name": "THUDM_glm-4-9b-chat", "test_category": "relevance", "valid": false, "error": ["Valid syntax. Successfully decode AST when it should not."], "error_type": "relevance_error:decoder_success", "model_result": "sports_ranking_get_champion\n{\"event\": \"World Series\", \"year\": 2020}", "decoded_result": [{"sports_ranking_get_champion": {"event": "World Series", "year": 2020}}]}
{"id": 204, "model_name": "THUDM_glm-4-9b-chat", "test_category": "relevance", "valid": false, "error": ["Valid syntax. Successfully decode AST when it should not."], "error_type": "relevance_error:decoder_success", "model_result": "get_player_score\n{\"player\": \"player A\", \"game\": \"Halo\"}", "decoded_result": [{"get_player_score": {"player": "player A", "game": "Halo"}}]}
{"id": 210, "model_name": "THUDM_glm-4-9b-chat", "test_category": "relevance", "valid": false, "error": ["Valid syntax. Successfully decode AST when it should not."], "error_type": "relevance_error:decoder_success", "model_result": "fetch_recipe\n{\"query\": \"building a PC\", \"numberOfResults\": 3, \"includeIngredients\": [\"motherboard\", \"CPU\", \"RAM\", \"graphics card\", \"power supply\"]}", "decoded_result": [{"fetch_recipe": {"query": "building a PC", "numberOfResults": 3, "includeIngredients": ["motherboard", "CPU", "RAM", "graphics card", "power supply"]}}]}
{"id": 214, "model_name": "THUDM_glm-4-9b-chat", "test_category": "relevance", "valid": false, "error": ["Valid syntax. Successfully decode AST when it should not."], "error_type": "relevance_error:decoder_success", "model_result": "restaurant_finder\n{\"cuisine\": \"pizza\", \"location\": \"Boston\", \"rating\": 3}", "decoded_result": [{"restaurant_finder": {"cuisine": "pizza", "location": "Boston", "rating": 3}}]}
{"id": 219, "model_name": "THUDM_glm-4-9b-chat", "test_category": "relevance", "valid": false, "error": ["Valid syntax. Successfully decode AST when it should not."], "error_type": "relevance_error:decoder_success", "model_result": "prepare_food_get_recipe\n{\"ingredients\": [\"flour\", \"sugar\", \"baking powder\", \"eggs\", \"milk\", \"vanilla extract\", \"chocolate\"], \"food_type\": \"cake\"}", "decoded_result": [{"prepare_food_get_recipe": {"ingredients": ["flour", "sugar", "baking powder", "eggs", "milk", "vanilla extract", "chocolate"], "food_type": "cake"}}]}
{"id": 224, "model_name": "THUDM_glm-4-9b-chat", "test_category": "relevance", "valid": false, "error": ["Valid syntax. Successfully decode AST when it should not."], "error_type": "relevance_error:decoder_success", "model_result": "grocery_shop_find_specific_product\n{\"city\": \"Chicago\", \"product\": \"sourdough bread\"}", "decoded_result": [{"grocery_shop_find_specific_product": {"city": "Chicago", "product": "sourdough bread"}}]}
{"id": 225, "model_name": "THUDM_glm-4-9b-chat", "test_category": "relevance", "valid": false, "error": ["Valid syntax. Successfully decode AST when it should not."], "error_type": "relevance_error:decoder_success", "model_result": "grocery_store_locate_nearby\n{\"location\": \"Los Angeles, CA\", \"store_type\": [\"Pet Store\"]}", "decoded_result": [{"grocery_store_locate_nearby": {"location": "Los Angeles, CA", "store_type": ["Pet Store"]}}]}
{"id": 228, "model_name": "THUDM_glm-4-9b-chat", "test_category": "relevance", "valid": false, "error": ["Valid syntax. Successfully decode AST when it should not."], "error_type": "relevance_error:decoder_success", "model_result": "calculate_sunrise\n{\"location\": \"Beijing\"}", "decoded_result": [{"calculate_sunrise": {"location": "Beijing"}}]}
{"id": 229, "model_name": "THUDM_glm-4-9b-chat", "test_category": "relevance", "valid": false, "error": ["Valid syntax. Successfully decode AST when it should not."], "error_type": "relevance_error:decoder_success", "model_result": "get_local_time\n{\"location\": \"Sydney\", \"format\": \"24\"}", "decoded_result": [{"get_local_time": {"location": "Sydney", "format": "24"}}]}
{"id": 231, "model_name": "THUDM_glm-4-9b-chat", "test_category": "relevance", "valid": false, "error": ["Valid syntax. Successfully decode AST when it should not."], "error_type": "relevance_error:decoder_success", "model_result": "find_hotel\n{\"location\": \"Miami\", \"max_price_per_night\": 100.0, \"pet_friendly\": true}", "decoded_result": [{"find_hotel": {"location": "Miami", "max_price_per_night": 100.0, "pet_friendly": true}}]}
{"id": 235, "model_name": "THUDM_glm-4-9b-chat", "test_category": "relevance", "valid": false, "error": ["Valid syntax. Successfully decode AST when it should not."], "error_type": "relevance_error:decoder_success", "model_result": "convert_currency\n{\"amount\": 10, \"from_currency\": \"inch\", \"to_currency\": \"meter\"}", "decoded_result": [{"convert_currency": {"amount": 10, "from_currency": "inch", "to_currency": "meter"}}]}
{"id": 237, "model_name": "THUDM_glm-4-9b-chat", "test_category": "relevance", "valid": false, "error": ["Valid syntax. Successfully decode AST when it should not."], "error_type": "relevance_error:decoder_success", "model_result": "get_flight_duration\n{\"start_city\": \"London\", \"destination_city\": \"Tokyo\", \"flight_type\": \"non-stop\"}", "decoded_result": [{"get_flight_duration": {"start_city": "London", "destination_city": "Tokyo", "flight_type": "non-stop"}}]}
{"id": 240, "model_name": "THUDM_glm-4-9b-chat", "test_category": "relevance", "valid": false, "error": ["Valid syntax. Successfully decode AST when it should not."], "error_type": "relevance_error:decoder_success", "model_result": "get_date\n{\"location_1\": \"San Francisco\", \"location_2\": \"Los Angeles\", \"unit\": \"kilometers\"}", "decoded_result": [{"get_date": {"location_1": "San Francisco", "location_2": "Los Angeles", "unit": "kilometers"}}]}